LICENSE
README.md
setup.cfg
setup.py
upgrade_oc/__init__.py
upgrade_oc/types.py
upgrade_oc.egg-info/PKG-INFO
upgrade_oc.egg-info/SOURCES.txt
upgrade_oc.egg-info/dependency_links.txt
upgrade_oc.egg-info/requires.txt
upgrade_oc.egg-info/top_level.txt
upgrade_oc.egg-info/zip-safe