Metadata-Version: 2.1
Name: upgrade-oc
Version: 1.1.0
Summary: Generic functions for handling upgrading services
Home-page: UNKNOWN
Author: Chris Nasr - Ouroboros Coding Inc.
Author-email: chris@ouroboroscoding.com
License: CUSTOM
Project-URL: Source, https://github.com/ouroboroscoding/upgrade-python
Project-URL: Tracker, https://github.com/ouroboroscoding/upgrade-python/issues
Keywords: upgrade,upgrading,automatic
Platform: UNKNOWN
Requires-Python: >=3.10
License-File: LICENSE
